webspray/lib/logger.py
webspray/lib/threadpool.py
webspray/webspray.py
webspray-1.0.0.dist-info/entry_points.txt
webspray-1.0.0.dist-info/LICENSE
webspray-1.0.0.dist-info/WHEEL
webspray-1.0.0.dist-info/METADATA
webspray-1.0.0.dist-info/RECORD
