Metadata-Version: 2.1
Name: webspray
Version: 1.0.0
Summary: Fuzz for hidden proxies, vhosts, and URLs across many hosts
Home-page: https://github.com/blacklanternsecurity/webspray
License: GPL-3.0
Author: TheTechromancer
Requires-Python: >=3.6,<4.0
Classifier: License :: OSI Approved :: GNU General Public License v3 (GPLv3)
Classifier: Programming Language :: Python :: 3
Classifier: Programming Language :: Python :: 3.6
Classifier: Programming Language :: Python :: 3.7
Classifier: Programming Language :: Python :: 3.8
Classifier: Programming Language :: Python :: 3.9
Requires-Dist: beautifulsoup4 (>=4.9.3,<5.0.0)
Requires-Dist: lxml (>=4.6.3,<5.0.0)
Requires-Dist: requests (>=2.25.1,<3.0.0)
Project-URL: Repository, https://github.com/blacklanternsecurity/webspray
